{
	"$meta": {
		"displayName": "Simplified Chinese",
		"selfName": "简体中文",
		"__comment": "Boilerplate",
		"maintainers": [
			"@meowzwr",
			null
		]
	},

	"actions": {
		"Select_None": "取消选择",
		"Select_Sibling": "选择同级骨骼",
		"Select_Children": "选择子骨骼",
		"Select_All": "选择所有实体",
		"Overlay_Toggle": "切换叠加层可见性",
		"History_Undo": "撤销",
		"History_Redo": "重做",
		"Gizmo_Toggle": "切换操作柄可见性",
		"Gizmo_ToggleMode": "切换世界/本地模式",
		"Gizmo_SetTranslateMode": "切换到位置模式",
		"Gizmo_SetRotateMode": "切换到旋转模式",
		"Gizmo_SetScaleMode": "切换到缩放模式",
		"Gizmo_SetUniversalMode": "切换到通用模式",
		"Camera_SetNext": "切换到下一个摄像机",
		"Camera_SetPrevious": "切换到上一个摄像机",
		"Camera_Work_Toggle": "切换工作摄像机",
		"Camera_Work_Forward": "工作摄像机前进",
		"Camera_Work_Left": "工作摄像机左移",
		"Camera_Work_Back": "工作摄像机后退",
		"Camera_Work_Right": "工作摄像机右移",
		"Camera_Work_Up": "工作摄像机上移",
		"Camera_Work_Down": "工作摄像机下移",
		"Camera_Work_Fast": "工作摄像机高速移动修饰键",
		"Camera_Work_Slow": "工作摄像机低速移动修饰键",
		"Pose_FlipPose": "翻转姿势",
		"Gizmo_MirrorRotation": "循环旋转模式（镜像/平行）",
		"Toolbar_ToggleWorkspace": "切换到工作区窗口",
		"Toolbar_ToggleObject": "切换到对象编辑器",
		"Toolbar_ToggleActor": "切换到角色编辑器",
		"Toolbar_TogglePose": "切换到姿势视图",
		"Toolbar_ToggleEnv": "切换到环境编辑器",
		"Toolbar_ToggleCamera": "切换到相机编辑器",
		"Toolbar_ToggleConfig": "切换到设置窗口"
	},

	"actors": {
		"pos_lock": "冻结角色位置"
	},

	"cameras": {
		"main": "主摄像机",
		"work": "工作摄像机",
		"camera": "相机",
		"new": "新摄像机",
		"selector": {
			"create": "创建新摄像机",
			"delete": "删除摄像机",
			"edit": "编辑摄像机",
			"edit_can_delete": "（或按住 Shift 删除）"
		}
	},

	"common": {
		"options": "选项",
		"appearance": "外观",
		"equipment": "装备",
		"unknown": "未知",
		"hide": "隐藏",
		"show": "显示",
		"entity": "实体",
		"chara_parts": {
			"body": "身体",
			"face": "面部",
			"hair": "头发",
			"gear": "装备",
			"accessories": "配饰",
			"weapons": "武器"
		},
		"rotation": "旋转",
		"position": "位置",
		"scale": "缩放"
	},

	"context": {
		"select": "选择",
		"unselect": "取消选择"
	},

	"transform": {
		"position": "位置",
		"rotation": "旋转\n按住 Shift 切换屏幕轨道。",
		"scale": "缩放"
	},

	"file": {
		"import": "导入...",
		"export": "导出...",
		"select": "选择要打开的文件...",
		"chara": {
			"name": "角色 (.chara)",
			"ctx_import": "导入外观...",
			"ctx_export": "导出外观...",
			"file": "文件",
			"apply": "应用于所选对象"
		},
		"pose": {
			"name": "姿势文件 (.pose)",
			"ctx_import": "导入姿势...",
			"ctx_import.group": "导入组...",
			"ctx_import.select": "导入所选内容...",
			"ctx_export": "导出姿势..."
		},
		"dialog": {
			"chara": {
				"filter": "角色文件",
				"load": "打开角色文件",
				"save": "保存角色文件"
			},
			"pose": {
				"filter": "姿势文件",
				"load": "打开姿势文件",
				"save": "保存姿势文件"
			},
			"light": {
				"filter": "灯光文件",
				"load": "打开灯光文件",
				"save": "保存灯光文件"
			},
			"mcdf": {
				"filter": "MCDF 文件",
				"load": "打开 MCDF 文件"
			},
			"image.load": "导入参考图像"
		}
	},

	"workspace": {
		"title": "Ktisis 工作区",
		"state": {
			"dormant": "正在等待场景...",
			"select_count": {
				"single": "%target% + %count% 个其他对象",
				"plural": "%target% + %count% 个其他对象",
				"none": "未选择."
			}
		},
		"posing": {
			"toggle": {
				"enable": "姿态模式已启用",
				"enable-blocked": "姿态模式已启用，按住SHIFT并点击以禁用。",
				"disable": "姿态模式已禁用"
			},
			"hint": {
				"enable": "骨骼操纵当前处于启用状态。",
				"enable-blocked": "要禁用，请按住SHIFT。",
				"disable": "骨骼操纵当前处于禁用状态。"
			}
		},
		"scene_tree": {
			"attached_to": "附着于",
			"reset_tooltip": "点击重置附着\n点击并拖拽设置新附着点"
		},
		"create_menu": {
			"actor": {
				"create": "创建新角色",
				"file": "从文件导入角色",
				"mcdf": "从 MCDF 导入角色",
				"overworld": "添加大世界角色"
			},
			"light": {
				"create": "创建新灯光",
				"point": "点光源",
				"spot": "聚光灯",
				"area": "区域光",
				"directional": "太阳（定向光）",
				"file": "从文件导入... (.ktlight)"
			},
			"reference": "添加参考图像"
		},
		"entity_menu": {
			"base": {
				"select": "选择",
				"deselect": "取消选择",
				"hierarchy": "选择层级",
				"presets": "预设...",
				"presets_save": "保存新预设",
				"detach": "解除附着",
				"rename": "重命名",
				"duplicate": "复制",
				"delete": "删除"
			},
			"actor": {
				"target": "目标",
				"edit": "编辑外观",
				"import": "导入...",
				"export": "导出...",
				"chara": "角色 (.chara)",
				"npc": "NPC",
				"pose": "姿势文件 (.pose)",
				"mcdf": "Mare 数据 (.mcdf)"
			},
			"ipc": {
				"submenu": "IPC 外观",
				"penumbra": {
					"collection": "Penumbra：分配合集",
					"invisible_skin": "Penumbra：隐形皮肤"
				},
				"glamourer": {
					"design": "Glamourer：应用设计"
				},
				"customize": {
					"profile": "Customize+：分配配置"
				},
				"revert": "还原所有 IPC 数据"
			},
			"pose": {
				"import": "导入姿势",
				"export": "导出姿势",
				"reference": "设为参考姿势"
			},
			"light": {
				"edit": "编辑灯光",
				"import": "导入灯光文件",
				"export": "导出灯光文件"
			}
		},
		"create": "新建...",
		"refresh_entities": "刷新场景实体",
		"edit_mode.hint": "选择编辑模式",
		"overlay.toggle": "切换屏幕叠加层"
	},

	"toolbar": {
		"title": "Ktisis 工具栏",
		"buttons": {
			"workspace": "工作区",
			"object": "对象编辑器",
			"actor": "角色编辑器",
			"posing": "姿势视图",
			"env": "环境编辑器",
			"camera": "相机编辑器",
			"scene": "场景编辑器",
			"config": "设置"
		}
	},

	"transform_edit": {
		"title": "变换编辑器",
		"actors": {
			"title": "参与角色"
		},
		"mode": {
			"world": "世界变换",
			"local": "本地变换"
		},
		"flags": {
			"parallel": "并行变换",
			"inverse": "逆向变换",
			"reflect": "镜像变换"
		},
		"sibling": {
			"available": "多选兄弟骨骼：%bone%",
			"unavailable": "骨骼 %bone% 没有兄弟骨骼",
			"multiple": "多选兄弟骨骼：%bone%\n只能在选择1个骨骼时选择兄弟骨骼！"
		},
		"gizmo": {
			"show": "显示旋转变换器",
			"hide": "隐藏旋转变换器"
		},
		"transforms": {
			"title": "骨骼变换",
			"parenting": "骨骼父级",
			"relative": "相对旋转"
		},
		"ik": {
			"title": "反向运动（IK）",
			"enable": "启用IK约束",
			"advanced": "高级参数",
			"enable_all": "全部启用",
			"disable_all": "全部禁用",
			"target": "选择",
			"edit": "配置",
			"active": "已启用",
			"ccd": {
				"gain": "增益",
				"iterations": "迭代次数"
			},
			"two_joints": {
				"enforce": "强制末端旋转",
				"mode": "变换模式：",
				"fixed": "固定目标",
				"relative": "骨骼相关",
				"gain": "增益：",
				"gain.shoulder": "肩部",
				"gain.elbow": "肘部",
				"gain.hand": "手部",
				"hinges": "铰链：",
				"hinges.min": "最小值",
				"hinges.max": "最大值",
				"hinges.axis": "轴向"
			}
		}
	},

	"preset_edit": {
		"title": "预设",
		"add": {
			"title": "添加新预设",
			"label": "预设名称",
			"save": "保存",
			"cancel": "取消"
		}
	},

	"chara_edit": {
		"title": "角色编辑器",
		"hint": "编辑外观与动画",
		"animation": {
			"tab": "动画",
			"controls": {
				"animationSelect": "动画",
				"idleSelect": "空闲姿势",
				"play": "播放",
				"reset": "重置",
				"loop": "循环",
				"playStart": "播放表情开始",
				"weapon": "拔出武器",
				"posLock": "冻结位置",
				"enableSpeed": "启用速度控制",
				"speedSlider": "播放速度",
				"scrub": "拖拽播放"
			},
			"poseExpression": {
				"title": "姿势表情",
				"warning": "⚠ 姿态模式当前已启用！",
				"brioWarning": "⚠ Brio当前已启用！当前的不兼容性阻止此功能正常工作 - 要加载姿势表情，请先禁用Brio。",
				"header": "警告：这是一个实验性功能！它将覆盖任何当前的面部姿势，并可能变形耳朵或其他面部部位。但是，您仍然可以撤销任何做出的更改。",
				"null": "未选择",
				"apply": "应用"
			}
		},
		"customize": {
			"tab": "外观",
			"iris": "小瞳孔",
			"primary": "主要特征",
			"face": "面部特征",
			"face_tat": "纹身",
			"facepaint_flip": "翻转面妆",
			"highlights": "高光",
			"eye_color": "眼睛颜色",
			"lipstick": "口红"
		},
		"equip.tab": "装备",
		"ipc": {
			"tab": "插件 (IPC)",
			"warn_actor": "请选择一个角色！",
			"mcdf_load": "加载 MCDF",
			"mcdf_tip": "MCDF（Mare Character Data File）包含捕获时应用于该玩家的全部 Penumbra、Glamourer\n与 CustomizePlus 数据。",
			"customize.title": "Customize+",
			"customize.profile": "C+ 配置",
			"penumbra": {
				"title": "Penumbra",
				"collection": "合集",
				"invisible_skin": "应用隐形皮肤"
			},
			"glamourer": {
				"title": "Glamourer",
				"design.select": "当前选择：",
				"design.none": "无",
				"design.apply": "应用"
			}
		},
		"misc": {
			"tab": "杂项",
			"model": "模型 ID",
			"model_tip": "按 Enter 提交",
			"opacity": "不透明度",
			"wetness": "湿润度覆盖",
			"wetness.weather": "天气湿润度",
			"wetness.swim": "游泳湿润度",
			"wetness.depth": "湿润深度"
		}
	},

	"object_edit": {
		"title": "对象编辑器",
		"actor": {
			"headers": {
				"actor": "角色",
				"adv": "高级（视线/IK）",
				"import": "导入角色外观",
				"gaze": "视线控制",
				"ik": "反向运动（IK）"
			},
			"gaze": {
				"linked": "已链接",
				"unlinked": "未链接",
				"camera": "相机追踪",
				"gizmo": "变换器追踪",
				"target": "选择目标角色",
				"targeting": "目标：",
				"unk": "未知",
				"null": "无目标"
			},
			"chara_edit": "角色编辑器",
			"export": "导出角色"
		},
		"pose": {
			"headers.pose": "姿势",
			"headers.reference": "参考姿势",
			"headers.import": "导入姿势文件",
			"export": "导出姿势",
			"flip": "翻转姿势",
			"stash": "暂存姿势",
			"stash.apply": "应用姿势",
			"stash.time": "姿势暂存于",
			"stash.from": "来自角色",
			"reference": "重置姿势",
			"reference_labels": {
				"all": "重置全部骨架",
				"null": "不适用",
				"body": "重置身体",
				"face": "重置面部",
				"hair": "重置头发",
				"custom": "重置骨架"
			}
		},
		"light": {
			"headers": {
				"light": "灯光",
				"shadows": "阴影"
			},
			"light": {
				"reflection": "启用反射",
				"type": "灯光类型",
				"color": "颜色",
				"intensity": "强度",
				"range": "范围",
				"import": "导入灯光设置",
				"export": "导出灯光设置",
				"spot.angle": "锥角",
				"spot.falloff": "衰减角",
				"area.angle": "光照角",
				"area.falloff": "衰减角",
				"falloff.type": "衰减类型",
				"falloff.power": "衰减强度"
			},
			"shadow": {
				"dynamic": "动态阴影",
				"chara": "投射角色阴影",
				"object": "投射物体阴影",
				"range": "阴影范围",
				"near": "阴影近裁剪",
				"far": "阴影远裁剪"
			}
		},
		"image": {
			"header": "参考图像",
			"visible": "启用",
			"load": "加载图像",
			"opacity": "不透明度"
		}
	},

	"camera_edit": {
		"title": "相机编辑器",
		"toggles": {
			"collide": "碰撞",
			"delimit": "解限",
			"ortho": "正交视图"
		},
		"sliders": {
			"rotation": "相机旋转",
			"zoom": "相机变焦",
			"distance": "相机距离",
			"ortho_zoom": "正交视图相机变焦"
		},
		"position": {
			"lock": "锁定到固定位置",
			"unlock": "解锁固定位置"
		},
		"orbit": {
			"lock": "锁定轨道目标",
			"unlock": "解锁轨道目标"
		},
		"offset": {
			"to_target": "偏移相机到目标模型",
			"from_base": "从基础位置偏移"
		},
		"pan": "相机平移",
		"angle": "相机轨道角度"
	},

	"env_edit": {
		"title": "环境编辑器",
		"enable": "启用",
		"weather": "天气",
		"time": "时间与日期",
		"advanced": "高级编辑",
		"fog": {
			"title": "雾",
			"color": "颜色",
			"distance": "距离",
			"thickness": "厚度",
			"opacity": "不透明度",
			"sky_vis": "天空可见度"
		},
		"housing": {
			"title": "房屋",
			"unavailable": "房屋灯光不可用。",
			"brightness": "亮度",
			"ssao": "SSAO"
		},
		"lighting": {
			"title": "光照",
			"sunlight": "阳光",
			"moonlight": "月光",
			"ambient": "环境光",
			"saturation": "饱和度",
			"temperature": "色温"
		},
		"particles": {
			"title": "粒子",
			"intensity": "强度",
			"size": "大小",
			"glow": "发光",
			"color": "颜色",
			"weight": "权重",
			"spread": "扩散",
			"speed": "速度",
			"spin": "旋转"
		},
		"sky": {
			"title": "天空",
			"edit_sky": "编辑天空盒",
			"texture": "天空纹理",
			"edit_clouds": "编辑云层",
			"top": "顶部云层",
			"side": "侧向云层",
			"color": "云层颜色",
			"shadow_color": "阴影颜色",
			"shadows": "阴影",
			"side_height": "侧向高度"
		},
		"rain": {
			"title": "雨",
			"intensity": "强度",
			"thickness": "厚度",
			"color": "颜色",
			"weight": "权重",
			"scattering": "散射",
			"raindrops": "雨滴"
		},
		"stars": {
			"title": "星星",
			"intensity": "强度",
			"constellations": "星座",
			"galaxy_intensity": "银河强度",
			"moon_color": "月亮颜色",
			"moon_brightness": "月亮亮度"
		},
		"water": {
			"title": "水",
			"water_one": "水体一",
			"water_two": "水体二",
			"water_three": "水体三",
			"water_four": "水体四"
		},
		"wind": {
			"title": "风",
			"direction": "方向",
			"angle": "角度",
			"speed": "速度"
		}
		
	},

	"pose_view": {
		"title": "姿势视图",
		"view_chooser": "视图：",
		"import": "导入",
		"export": "导出",
		"no_target": "请选择一个角色以开始编辑其姿势。"
	},

	"chara_import": {
		"title": "导入外观",
		"header": "正在为以下对象导入外观",
		"apply": "应用"
	},
	"pose_import": {
		"title": "导入姿势",
		"header": "正在为以下对象导入姿势",
		"apply": "应用",
		"transforms.header": "变换：",
		"modes": {
			"header": "模式：",
			"selective_import": "应用所选骨骼",
			"descendants": "包含子骨骼",
			"anchor": "锚定组位置",
			"exclude_ears": "排除耳朵骨骼",
			"warn_face_compat": "由于与所选角色不兼容，所选姿势文件中的面部将不会被导入。",
			"warn_ik_on": "反向运动（IK）已启用！这可能会覆盖导入的肢体。"
		}
	},

	"config": {
		"title": "Ktisis 设置",
		"categories": {
			"title": "个性化",
			"allow_nsfw": "显示NSFW骨骼",
			"hint_nsfw": "需要IVCS、YAS或任何自定义骨架。",
			"show_all_viera_ears": "显示未使用的耳朵骨骼",
			"hint_viera_ears": "显示所有维埃拉族耳朵的骨骼，包括其他耳朵选项的骨骼。",
			"show_friendly_bone_names": "显示友好的骨骼名称",
			"hint_friendly_bones": "在可用的情况下为骨骼使用本地化名称，而不是SE默认名称。",
			"header": "骨骼类别：",
			"editor": {
				"color_header": "颜色：",
				"group_color": "组颜色",
				"bone_color": "骨骼颜色",
				"subcategories": "应用于子类别",
				"link_colors": "链接组与骨骼的颜色"
			}
		},
		"gizmo": {
			"title": "操作柄",
			"flip": "面向相机翻转轴",
			"raySnap": "按住 Shift 进行射线吸附",
			"rayHint": "移动 XYZ 平移操作柄时，按住 Shift 可将对象吸附到世界表面",
			"holdSnap": "按住 Ctrl 吸附操作柄数值（再加 Shift 提高精度）",
			"hintHoldSnap": "拖拽鼠标时将操作柄数值吸附到最近的刻度",
			"2d_scale": "2D 操作柄缩放",
			"header": "操作柄样式：",
			"disabled": "当前版本中操作柄样式功能暂不可用，等待 Dalamud 更新！",
			"editor": {
				"general": {
					"title": "常规",
					"dir_x": "方向 X",
					"dir_y": "方向 Y",
					"dir_z": "方向 Z",
					"active": "选中颜色",
					"inactive": "未激活颜色"
				},
				"position": {
					"title": "位置",
					"line_thick": "线条厚度",
					"line_color": "线条颜色",
					"axis_thick": "坐标轴填充图案厚度",
					"axis_color": "坐标轴填充图案颜色",
					"circle_size": "中心圆大小",
					"arrow_size": "箭头尺寸",
					"plane_x": "平面 X",
					"plane_y": "平面 Y",
					"plane_z": "平面 Z"
				},
				"rotation": {
					"title": "旋转",
					"inner_thick": "内部线条厚度",
					"outer_thick": "外部线条厚度",
					"border_color": "激活边框的颜色",
					"fill_color": "激活的填充颜色"
				},
				"scale": {
					"title": "缩放",
					"line_thick": "线条厚度",
					"line_color": "激活线条的颜色",
					"circle_size": "圆圈尺寸"
				},
				"text": {
					"title": "文本",
					"color": "文本颜色",
					"shadow_color": "阴影颜色"
				},
				"undo": "重置为默认值"
			}
		},
		"overlay": {
			"title": "叠加层",
			"header": "配置骨骼叠加层：",
			"lines": {
				"draw": "在骨骼上绘制线",
				"draw_gizmo": "使用变换器时在骨骼上绘制线",
				"thick": "线条粗细",
				"opacity": "线条不透明度",
				"opacity_gizmo": "使用变换器时的线条不透明度"
			},
			"dots": {
				"draw_gizmo": "使用变换器时绘制点",
				"radius": "点半径"
			}
		},
		"references": {
			"draw_title": "为参考图像绘制标题。"
		},
		"workspace": {
			"title": "通用",
			"header": "工作区设置",
			"init": "进入 GPose 时打开工作区",
			"toggleOpenWindows": "UI 按钮切换窗口开关",
			"toolbar": "使用 Ktisis 工具栏",
			"hintToolbar": "实验功能：将 Ktisis 各编辑器整合到单一窗口的替代界面。\n该选项仍在积极开发中，欢迎反馈！",
			"editOnSelect": "从工作区选中对象时打开对象编辑器",
			"closeOnDeselect": "未选中任何对象时关闭对象编辑器",
			"incognitoPlayerNames": "隐身模式",
			"hintIncognito": "在角色列表与集体拍照窗口中隐藏所有玩家名称",
			"hintInit": "若关闭，可在 GPose 中输入 /ktisis 打开 Ktisis 工作区",
			"windowHeader": "窗口行为",
			"legacyHeader": "传统界面选项（v0.3 发布后将弃用）",
			"legacyWindows": "优先使用传统窗口行为",
			"legacyWindowHint": "控制各窗口是否以及如何仅针对当前目标角色",
			"legacyPoseTabs": "姿势视图：通过标签页切换角色（而非工作区）",
			"legacyLightEditor": "优先使用传统灯光编辑器",
			"legacyLightHint": "允许单独打开灯光编辑器窗口（已迁至对象编辑器）",
			"confirmExit": "退出姿势模式时需按住 Shift 确认",
			"AutoResizeObjectEditor": "打开新下拉菜单时自动扩展对象编辑器高度",
			"hint_AutoResizeObj": "开启后将无法手动调整编辑器高度，仍可调整宽度",
			"workcam": {
				"speed": "工作相机速度",
				"fastMulti": "工作相机快速倍率",
				"slowMulti": "工作相机慢速倍率",
				"vertMulti": "工作相机上下速度倍率",
				"sens": "工作相机鼠标灵敏度"
			},
			"customLocations": {
				"header": "自定义文件位置",
				"description": "管理文件对话框中的自定义文件夹快捷位置。",
				"columnName": "名称",
				"columnPath": "路径",
				"browse": "浏览",
				"remove": "移除",
				"add": "添加新位置",
				"moving": "移动 %name%",
				"selectFolder": "选择文件夹"
			},
			"defaultLocation": {
				"remove": "取消将此文件夹设为默认",
				"add": "将此文件夹设为使用文件浏览器时的默认打开位置"
			}
		},
		"input": {
			"title": "输入",
			"enable": "启用按键绑定",
			"help": "点击按键绑定以修改它们。右键点击以清除。必须启用按键绑定才能编辑。",
			"blockLeft": "左键点击时禁用GPose更改目标",
			"blockRight": "右键点击时禁用GPose更改目标",
			"scrollAllow": "为变换滑块启用滚轮输入",
			"scrollMod": "需要按住ALT键才能使用滚轮控制变换滑块",
			"cameras": {
				"title": "相机",
				"header": "相机控制："
			},
			"gizmo": {
				"title": "操作柄",
				"header": "操作柄快捷键："
			},
			"toolbar": {
				"title": "工具栏",
				"header": "工具栏快捷键："
			}
		},
		"autosave": {
			"title": "自动保存",
			"enable": "启用自动保存",
			"clear": "退出时清除自动保存",
			"ondisable": "禁用姿势模式时始终保存",
			"disconnect": "服务器断开连接时始终保存",
			"interval": "保存间隔",
			"count": "保存计数",
			"path": "保存路径",
			"dir": "文件夹名称"
		},
		"presets": {
			"title": "预设",
			"description": "在下方查看和编辑您定义的骨骼可见性预设。",
			"defaults": "右键点击任何预设将其标记为默认。默认预设将初始为任何GPose角色启用。",
			"delete_tooltip": "按住SHIFT以删除",
			"delete": "删除",
			"rename": "重命名"
		},
		"poseview": {
			"title": "姿势视图",
			"description": "在下方选择您自己的图像以在姿势视图界面中使用。",
			"body": "身体",
			"armor": "护甲（服装）",
			"ears": "耳朵（维埃拉）",
			"face": "脸部",
			"hands": "手部",
			"lips": "嘴唇",
			"mouth": "嘴部",
			"tail": "尾巴",
			"linkout": {
				"description": "在此下载模板图像：",
				"button": "GitHub",
				"link": "https://github.com/ktisis-tools/Ktisis/tree/v0.3/main/Ktisis/Data/Images/Templates"
			}
		},
		"offsets": {
			"title": "骨骼偏移",
			"description": "导入与编辑可视化骨骼偏移",
			"help": "在下方为骨骼设置平移后，Ktisis界面上该骨骼的可点击节点位置会被调整为新值。",
			"selected": "已选骨骼",
			"ui": {
				"copy_all": "全部复制到剪贴板",
				"load_all": "从剪贴板加载全部",
				"load_all_warning": "警告：此操作将替换你当前的全部偏移配置。\n按住CTRL+Shift确认。",
				"add_bone": "添加骨骼偏移",
				"load_legacy": "加载旧版偏移",
				"copy_bone": "复制该骨骼偏移值",
				"load_bone": "粘贴该骨骼偏移值",
				"clear_bone": "Shift+点击清除该骨骼偏移"
			},
			"race_sex": {
				"101": "中原男性",
				"201": "中原女性",
				"301": "高地男性",
				"401": "高地女性",
				"501": "精灵男性",
				"601": "精灵女性",
				"701": "猫魅男性",
				"801": "猫魅女性",
				"901": "鲁加男性",
				"1001": "鲁加女性",
				"1101": "拉拉菲尔男性",
				"1201": "拉拉菲尔女性",
				"1301": "敖龙男性",
				"1401": "敖龙女性",
				"1501": "赫尔加男性",
				"1601": "赫尔加女性",
				"1701": "维埃拉男性",
				"1801": "维埃拉女性"
			}
		},
		"misc.title": "杂项",
		"about": {
			"title": "关于",
			"header": "关于Ktisis",
			"readme": "Ktisis是一款强大的拍照姿态工具，可在FFXIV的GPose模式下，通过点击骨骼并自由移动实现对角色的全方位造型。工具还支持动画控制与角色编辑，我们的目标是让造型操作更加便捷易用。",
			"gitLinkout": {
				"description": "欢迎在GitHub提交问题或参与开发：",
				"button": "GitHub",
				"link": "https://github.com/ktisis-tools/Ktisis/"
			},
			"discordLinkout": {
				"description": "加入我们的Discord社区，获取技术支持、分享截图、获取更新日志等：",
				"button": "Discord",
				"link": "https://discord.com/invite/kUG3W8B8Ny/"
			}
		},
		"language": {
			"title": "语言",
			"autoselect": "自动设置语言",
			"selector": "强制使用语言"
		}
	},

	"migrator": {
		"title": "Ktisis v0.4 设置",
		"mainWindow": {
			"main_Desc": "感谢使用 Ktisis！v0.4 现已成为稳定版本。\n此迁移工具可帮助你转移 Ktisis Alpha 设置，或更新 Ktisis 工作区设置。",
			"skip": "跳过迁移",
			"skip_desc": "跳过迁移并以默认设置启动 v0.4。\n你将无法再次访问迁移工具，所有旧设置将被丢弃。",
			"v3": {
				"from": "我来自 v0.3！",
				"from_desc": "基于 v0.3 的 Ktisis 设置开始迁移（测试版）。\n如有适用，将忽略 v0.2 的所有旧版设置。",
				"main_Desc": "自我们开始开发 v0.3 以来变化很大，在开发 Ktisis 的过程中，部分功能已更改或改进。\n以下设置有了新的默认值，你可以保留旧配置，也可以使用新的推荐值。",
				"testing": "v0.4 已正式发布，建议你在 Dalamud 中关闭「接收测试版本」。",
				"installer": "你可以在此打开插件安装器以更改 Ktisis 的此设置："
			},
			"v2": {
				"from": "我来自 v0.2！",
				"from_desc": "基于 v0.2 的 Ktisis 设置开始迁移（Alpha）。\n如有适用，将覆盖你现有的 v0.3 设置。",
				"main_Desc": "感谢使用 Ktisis！v0.3 是我们的最新版本，凝聚了多位作者超过 2 年的改进工作。\nv0.2 中几乎所有代码都已更新，感谢你的持续支持。这些重写为未来的开发奠定了稳定基础。\n除了 v0.2 的新功能外，我们还有许多更大的想法待探索，敬请期待！",
				"migration_desc": "此更新工具会将 v0.2 的设置尽可能转换为 v0.3。请注意各页面的工具提示与说明。\n你可以在每页自行覆盖，迁移后也可随时更改这些设置。",
				"wiki": "要了解 Ktisis v0.2 与 v0.3 之间的变化，请访问我们的 Wiki 文档："
			}
		},
		"v3": {
			"openWindowToggle": "切换窗口开关",
			"openWindowToggleSub": "启用后，工作区按钮可同时打开和关闭对应的窗口。",
			"toolbar": "使用 Ktisis 工具栏",
			"toolbarSub": "Ktisis 工具栏是一种替代 UI 模式，推荐给 v0.2 用户以及更习惯紧凑单窗口界面的用户。",
			"keybinds": "启用快捷键"
		},
		"v2": {
			"editor": {
				"header": "编辑器设置",
				"nsfw": "显示 NSFW 骨骼",
				"nsfwTooltip": "v0.2 设置：屏蔽 NSFW 骨骼",
				"incognito": "隐身模式",
				"incognitoTooltip": "v0.2 设置：隐藏玩家名称",
				"incognitoSub": "分享 UI 截图时建议启用此选项，以保护玩家隐私。",
				"toolbar": "使用 Ktisis 工具栏",
				"toolbarSub": "Ktisis 工具栏是一种替代 UI 模式，推荐给 v0.2 用户以及更习惯紧凑单窗口界面的用户。"
			},
			"input": {
				"header": "输入设置",
				"detail": "你的 v0.2 按键绑定将尽可能迁移到 v0.3 对应项。你可以随时在「设置 > 输入」中更新。",
				"keybinds": "启用按键绑定",
				"leftClick": "左键点击时禁用 GPose 更改目标",
				"rightClick": "右键点击时禁用 GPose 更改目标"
			},
			"overlay": {
				"header": "叠加层设置",
				"detail": "迁移后可在「设置 > 个性化」中自定义各类骨骼的颜色与透明度。",
				"drawLines": "在骨骼上绘制线",
				"drawLinesGizmo": "使用操作柄时在骨骼上绘制线",
				"drawDotsGizmo": "使用操作柄时在骨骼上绘制点",
				"allowAxisFlip": "面向相机翻转轴",
				"allowAxisFlipTip": "允许 3D 操作柄根据 GPose 相机角度重新定向",
				"lineThickness": "线条粗细",
				"lineOpacity": "线条不透明度",
				"lineOpacityUsing": "使用时的线条不透明度",
				"dotRadius": "点半径"
			},
			"autosave": {
				"header": "自动保存设置",
				"detail": "迁移后可在「设置 > 自动保存」中进一步自定义自动保存的目标文件夹与命名方案。",
				"enabled": "已启用",
				"interval": "间隔",
				"intervalTip": "每次自动保存之间等待的秒数",
				"numToSave": "自动保存最大数量",
				"clearOnExit": "退出时清除",
				"autoOnDC": "断开连接时自动保存"
			},
			"camera": {
				"header": "工作相机设置",
				"sens": "灵敏度",
				"movSpeed": "移动速度",
				"fastMulti": "快速倍率",
				"slowMulti": "慢速倍率",
				"vertMulti": "垂直倍率"
			}
		},
		"next": "下一步",
		"finish": "完成"
	},
	
	"bone": {
		"n_root": "根骨骼 (Root)",
		"n_hara": "腹部 (Abdomen)",
		"n_throw": "投掷物 (Throw)",
		"j_kosi": "腰部 (Waist)",
		"j_sebo_a": "腰椎 (Lumbar)",
		"j_asi_a_l": "左腿 (Left Leg)",
		"j_asi_a_r": "右腿 (Right Leg)",
		"j_buki2_kosi_l": "左枪套 (Left Holster)",
		"j_buki2_kosi_r": "右枪套 (Right Holster)",
		"j_buki_kosi_l": "左刀鞘 (Left Sheathe)",
		"j_buki_kosi_r": "右刀鞘 (Right Sheathe)",
		"j_sebo_b": "胸椎 (Thoracic)",
		"j_sk_b_a_l": "衣服后侧左A (Left Cloth Back A)",
		"j_sk_b_a_r": "衣服后侧右A (Right Cloth Back A)",
		"j_sk_f_a_l": "衣服前侧左A (Left Cloth Front A)",
		"j_sk_f_a_r": "衣服前侧右A (Right Cloth Front A)",
		"j_sk_s_a_l": "衣服左侧A (Left Cloth Side A)",
		"j_sk_s_a_r": "衣服右侧A (Right Cloth Side A)",
		"j_asi_b_l": "左膝盖 (Left Knee)",
		"j_asi_b_r": "右膝盖 (Right Knee)",
		"j_mune_l": "左乳房 (Left Breast)",
		"j_mune_r": "右乳房 (Right Breast)",
		"j_sebo_c": "颈椎 (Cervical)",
		"j_sk_b_b_l": "衣服后侧左B (Left Cloth Back B)",
		"j_sk_b_b_r": "衣服后侧右B (Right Cloth Back B)",
		"j_sk_f_b_l": "衣服前侧左B (Left Cloth Front B)",
		"j_sk_f_b_r": "衣服前侧右B (Right Cloth Front B)",
		"j_sk_s_b_l": "衣服左侧B (Left Cloth Side B)",
		"j_sk_s_b_r": "衣服右侧B (Right Cloth Side B)",
		"j_asi_c_l": "左小腿 (Left Calf)",
		"j_asi_c_r": "右小腿 (Right Calf)",
		"j_buki_sebo_l": "左护胸 (Left Scabbard)",
		"j_buki_sebo_r": "右护胸 (Right Scabbard)",
		"j_kubi": "颈部 (Neck)",
		"j_sako_l": "左锁骨 (Left Clavicle)",
		"j_sako_r": "右锁骨 (Right Clavicle)",
		"j_sk_b_c_l": "衣服后侧左C (Left Cloth Back C)",
		"j_sk_b_c_r": "衣服后侧右C (Right Cloth Back C)",
		"j_sk_f_c_l": "衣服前侧左C (Left Cloth Front C)",
		"j_sk_f_c_r": "衣服前侧右C (Right Cloth Front C)",
		"j_sk_s_c_l": "衣服左侧C (Left Cloth Side C)",
		"j_sk_s_c_r": "衣服右侧C (Right Cloth Side C)",
		"n_hizasoubi_l": "左护膝 (Left Poleyn)",
		"n_hizasoubi_r": "右护膝 (Right Poleyn)",
		"j_asi_d_l": "左脚 (Left Foot)",
		"j_asi_d_r": "右脚 (Right Foot)",
		"j_kao": "头部 (Head)",
		"j_ude_a_l": "左臂 (Left Arm)",
		"j_ude_a_r": "右臂 (Right Arm)",
		"n_kataarmor_l": "左肩甲 (Left Pauldron)",
		"n_kataarmor_r": "右肩甲 (Right Pauldron)",
		"j_asi_e_l": "左脚趾 (Left Toes)",
		"j_asi_e_r": "右脚趾 (Right Toes)",
		"j_kami_a": "头发A (Hair A)",
		"j_kami_f_l": "左前发 (Left Hair Front)",
		"j_kami_f_r": "右前发 (Right Hair Front)",
		"j_mimi_l": "左耳 (Left Ear)",
		"j_mimi_r": "右耳 (Right Ear)",
		"j_ude_b_l": "左前臂 (Left Forearm)",
		"j_ude_b_r": "右前臂 (Right Forearm)",
		"n_hkata_l": "左肩 (Left Shoulder / Twist)",
		"n_hkata_r": "右肩 (Right Shoulder / Twist)",
		"j_kami_b": "头发B (Hair B)",
		"j_te_l": "左手 (Left Hand)",
		"j_te_r": "右手 (Right Hand)",
		"n_buki_tate_l": "左盾牌 (Left Shield)",
		"n_buki_tate_r": "右盾牌 (Right Shield)",
		"n_ear_a_l": "左耳环A (Left Earring A)",
		"n_ear_a_r": "右耳环A (Right Earring A)",
		"n_hhiji_l": "左肘 (Left Elbow / Twist)",
		"n_hhiji_r": "右肘 (Right Elbow / Twist)",
		"n_hijisoubi_l": "左护肘 (Left Couter)",
		"n_hijisoubi_r": "右护肘 (Right Couter)",
		"n_hte_l": "左手腕 (Left Wrist)",
		"n_hte_r": "右手腕 (Right Wrist)",
		"j_hito_a_l": "左食指A (Left Index A)",
		"j_hito_a_r": "右食指A (Right Index A)",
		"j_ko_a_l": "左小指A (Left Pinky A)",
		"j_ko_a_r": "右小指A (Right Pinky A)",
		"j_kusu_a_l": "左无名指A (Left Ring A)",
		"j_kusu_a_r": "右无名指A (Right Ring A)",
		"j_naka_a_l": "左中指A (Left Middle A)",
		"j_naka_a_r": "右中指A (Right Middle A)",
		"j_oya_a_l": "左拇指A (Left Thumb A)",
		"j_oya_a_r": "右拇指A (Right Thumb A)",
		"n_buki_l": "左武器 (Left Weapon)",
		"n_buki_r": "右武器 (Right Weapon)",
		"n_ear_b_l": "左耳环B (Left Earring B)",
		"n_ear_b_r": "右耳环B (Right Earring B)",
		"j_hito_b_l": "左食指B (Left Index B)",
		"j_hito_b_r": "右食指B (Right Index B)",
		"j_ko_b_l": "左小指B (Left Pinky B)",
		"j_ko_b_r": "右小指B (Right Pinky B)",
		"j_kusu_b_l": "左无名指B (Left Ring B)",
		"j_kusu_b_r": "右无名指B (Right Ring B)",
		"j_naka_b_l": "左中指B (Left Middle B)",
		"j_naka_b_r": "右中指B (Right Middle B)",
		"j_oya_b_l": "左拇指B (Left Thumb B)",
		"j_oya_b_r": "右拇指B (Right Thumb B)",
		"n_sippo_a": "尾巴A (Tail A)",
		"n_sippo_b": "尾巴B (Tail B)",
		"n_sippo_c": "尾巴C (Tail C)",
		"n_sippo_d": "尾巴D (Tail D)",
		"n_sippo_e": "尾巴E (Tail E)",
		"j_ago": "下颌 (Jaw)",
		"j_sita": "舌头 (Tongue)",
		"j_f_dmab_l": "左下眼睑 (Left Lower Eyelid)",
		"j_f_dmab_r": "右下眼睑 (Right Lower Eyelid)",
		"j_f_eye_l": "左眼 (Left Eye)",
		"j_f_eye_r": "右眼 (Right Eye)",
		"j_f_hana": "鼻子 (Nose)",
		"j_f_lip_l": "左唇 (Left Lips)",
		"j_f_lip_r": "右唇 (Right Lips)",
		"j_f_memoto": "额骨桥 (Bridge)",
		"j_f_miken_l": "左眉心 (Left Brow)",
		"j_f_miken_r": "右眉心 (Right Brow)",
		"j_f_ulip_a": "上唇A (Upper Lip A)",
		"j_f_umab_l": "左上眼睑 (Left Upper Eyelid)",
		"j_f_umab_r": "右上眼睑 (Right Upper Eyelid)",
		"j_f_dlip_a": "下唇A (Lower Lip A)",
		"j_f_ulip_b": "上唇B (Upper Lip B)",
		"j_f_dlip_b": "下唇B (Lower Lip B)",
		"j_zera_a_l": "左耳部A (Left Ear 1A)",
		"j_zera_a_r": "右耳部A (Right Ear 1A)",
		"j_zera_b_l": "左耳部B (Left Ear 1B)",
		"j_zera_b_r": "右耳部B (Right Ear 1B)",
		"j_zerb_a_l": "左耳部A (Left Ear 2A)",
		"j_zerb_a_r": "右耳部A (Right Ear 2A)",
		"j_zerb_b_l": "左耳部B (Left Ear 2B)",
		"j_zerb_b_r": "右耳部B (Right Ear 2B)",
		"j_zerc_a_l": "左耳部A (Left Ear 3A)",
		"j_zerc_a_r": "右耳部A (Right Ear 3A)",
		"j_zerc_b_l": "左耳部B (Left Ear 3B)",
		"j_zerc_b_r": "右耳部B (Right Ear 3B)",
		"j_zerd_a_l": "左耳部A (Left Ear 4A)",
		"j_zerd_a_r": "右耳部A (Right Ear 4A)",
		"j_zerd_b_l": "左耳部B (Left Ear 4B)",
		"j_zerd_b_r": "右耳部B (Right Ear 4B)",
		"j_f_hige_l": "左胡须 (Left Whiskers)",
		"j_f_hige_r": "右胡须 (Right Whiskers)",
		"j_f_uago": "上唇A (Upper Lip A)",
		"j_f_ulip": "上唇B (Upper Lip B)",
		"n_f_lip_l": "左唇 (Left Lips)",
		"n_f_lip_r": "右唇 (Right Lips)",
		"n_f_ulip_l": "左上唇 (Left Upper Lip)",
		"n_f_ulip_r": "右上唇 (Right Upper Lip)",
		"j_f_dlip": "下唇 (Lower Lip)",
		"j_ex_met_va": "面罩 (Visor)",
		"mh_n_hara": "主手 (Main Hand)",
		"oh_n_hara": "副手 (Off Hand)",
		"j_half_l": "左半部分 (Left Half)",
		"j_half_r": "右半部分 (Right Half)",

		"j_f_ago": "下颌",
		"j_f_dago": "仅下颌",
		"j_f_bero_01": "舌头A",
		"j_f_bero_02": "舌头B",
		"j_f_bero_03": "舌头C",
		"j_f_hagukiup": "上牙",
		"j_f_hagukidn": "下牙",
		"j_f_dlip_01_l": "下唇左中部A",
		"j_f_dlip_02_l": "下唇左中部B",
		"j_f_dlip_01_r": "下唇右中部A",
		"j_f_dlip_02_r": "下唇右中部B",
		"j_f_ulip_01_l": "上唇左中部A",
		"j_f_ulip_02_l": "上唇左中部B",
		"j_f_ulip_01_r": "上唇右中部A",
		"j_f_ulip_02_r": "上唇右中部B",
		"j_f_dmlip_01_l": "下唇左侧A",
		"j_f_dmlip_02_l": "下唇左侧B",
		"j_f_dmlip_01_r": "下唇右侧A",
		"j_f_dmlip_02_r": "下唇右侧B",
		"j_f_umlip_01_l": "上唇左侧A",
		"j_f_umlip_02_l": "上唇左侧B",
		"j_f_umlip_01_r": "上唇右侧A",
		"j_f_umlip_02_r": "上唇右侧B",
		"j_f_uslip_l": "上唇左角A",
		"j_f_dslip_l": "下唇左角A",
		"j_f_uslip_r": "上唇右角A",
		"j_f_dslip_r": "下唇右角A",

		"j_f_mab_l": "左眼皮",
		"j_f_mab_r": "右眼皮",
		"j_f_eyepuru_l": "左眼拉动",
		"j_f_eyepuru_r": "右眼拉动",
		"j_f_mabup_01_l": "左上眼皮",
		"j_f_mabdn_01_l": "左下眼皮",
		"j_f_mabup_01_r": "右上眼皮",
		"j_f_mabdn_01_r": "右下眼皮",
		"j_f_mabup_02out_l": "左上外眼角",
		"j_f_mabdn_02out_l": "左下外眼角",
		"j_f_mabup_03in_l": "左上内眼角",
		"j_f_mabdn_03in_l": "左下内眼角",
		"j_f_mabup_02out_r": "右上外眼角",
		"j_f_mabdn_02out_r": "右下外眼角",
		"j_f_mabup_03in_r": "右上内眼角",
		"j_f_mabdn_03in_r": "右下内眼角",

		"j_f_mayu_l": "左外眉",
		"j_f_mayu_r": "右外眉",
		"j_f_mmayu_l": "左中眉",
		"j_f_mmayu_r": "右中眉",
		"j_f_miken_01_l": "左内眉A",
		"j_f_miken_02_l": "左内眉B",
		"j_f_miken_01_r": "右内眉A",
		"j_f_miken_02_r": "右内眉B",

		"j_f_face": "面部",
		"j_f_hoho_l": "左上颊",
		"j_f_hoho_r": "右上颊",
		"j_f_dhoho_l": "左中颊",
		"j_f_dhoho_r": "右中颊",
		"j_f_shoho_l": "左下颊",
		"j_f_shoho_r": "右下颊",
		"j_f_dmemoto_l": "左前颊",
		"j_f_dmemoto_r": "右前颊",
		"j_f_uhana": "鼻梁",
		"j_f_hana_l": "左鼻孔",
		"j_f_hana_r": "右鼻孔",
		"j_f_dmiken_l": "左鼻梁",
		"j_f_dmiken_r": "右鼻梁",

		"j_ex_met_vb": "面甲",

		"iv_asi_oya_a_l": "IVCS 左脚大趾 A",
		"iv_asi_oya_b_l": "IVCS 左脚大趾 B",
		"iv_asi_hito_a_l": "IVCS 左脚食趾 A",
		"iv_asi_hito_b_l": "IVCS 左脚食趾 B",
		"iv_asi_naka_a_l": "IVCS 左脚趾中节 A",
		"iv_asi_naka_b_l": "IVCS 左脚趾中节 B",
		"iv_asi_kusu_a_l": "IVCS 左脚无名趾 A",
		"iv_asi_kusu_b_l": "IVCS 左脚无名趾 B",
		"iv_asi_ko_a_l": "IVCS 左脚小趾 A",
		"iv_asi_ko_b_l": "IVCS 左脚小趾 B",

		"iv_asi_oya_a_r": "IVCS 右脚大趾 A",
		"iv_asi_oya_b_r": "IVCS 右脚大趾 B",
		"iv_asi_hito_a_r": "IVCS 右脚食趾 A",
		"iv_asi_hito_b_r": "IVCS 右脚食趾 B",
		"iv_asi_naka_a_r": "IVCS 右脚趾中节 A",
		"iv_asi_naka_b_r": "IVCS 右脚趾中节 B",
		"iv_asi_kusu_a_r": "IVCS 右脚无名趾 A",
		"iv_asi_kusu_b_r": "IVCS 右脚无名趾 B",
		"iv_asi_ko_a_r": "IVCS 右脚小趾 A",
		"iv_asi_ko_b_r": "IVCS 右脚小趾 B",

		"iv_hito_c_l": "IVCS 左手食指 C",
		"iv_naka_c_l": "IVCS 左手中指 C",
		"iv_kusu_c_l": "IVCS 左手无名指 C",
		"iv_ko_c_l": "IVCS 左手小指 C",
		"iv_hito_c_r": "IVCS 右手食指 C",
		"iv_naka_c_r": "IVCS 右手中指 C",
		"iv_kusu_c_r": "IVCS 右手无名指 C",
		"iv_ko_c_r": "IVCS 右手小指 C",

		"iv_nitoukin_l": "IVCS 左肱二头肌",
		"iv_nitoukin_r": "IVCS 右肱二头肌",

		"iv_c_mune_l": "IVCS 左胸",
		"iv_c_mune_r": "IVCS 右胸",

		"iv_kougan_l": "IVCS 左阴囊",
		"iv_kougan_r": "IVCS 右阴囊",
		"iv_ochinko_a": "IVCS 阴茎 A",
		"iv_ochinko_b": "IVCS 阴茎 B",
		"iv_ochinko_c": "IVCS 阴茎 C",
		"iv_ochinko_d": "IVCS 阴茎 D",
		"iv_ochinko_e": "IVCS 阴茎 E",
		"iv_ochinko_f": "IVCS 阴茎 F",

		"iv_kuritto": "IVCS 阴蒂",
		"iv_inshin_l": "IVCS 左阴唇",
		"iv_inshin_r": "IVCS 右阴唇",
		"iv_omanko": "IVCS 阴道",

		"iv_koumon": "IVCS 肛门",
		"iv_koumon_l": "IVCS 肛门左侧",
		"iv_koumon_r": "IVCS 肛门右侧",
		"iv_shiri_l": "IVCS 左臀",
		"iv_shiri_r": "IVCS 右臀"
	},

	"boneCategory": {
		"Head": "头部",
		"Hair": "头发",
		"Ears": "耳朵",
		"LeftEar": "左耳",
		"RightEar": "右耳",
		"Face": "脸部",
		"Brow": "额头",
		"LeftBrow": "左眉",
		"RightBrow": "右眉",
		"Eyebrows": "眉毛",
		"Eyes": "眼睛",
		"LeftEye": "左眼",
		"RightEye": "右眼",
		"Eyelids": "眼睑",
		"LeftEyelid": "左眼眼睑",
		"RightEyelid": "右眼眼睑",
		"Mouth": "嘴",
		"UpperMouth": "嘴（上）",
		"LowerMouth": "嘴（下）",
		"UpperLip": "上唇",
		"LowerLip": "下唇",
		"Cheeks": "脸颊",
		"LeftCheek": "左脸颊",
		"RightCheek": "右脸颊",
		"Body": "身体",
		"Arms": "手臂",
		"LeftArm": "左臂",
		"LeftHand": "左手",
		"RightArm": "右臂",
		"RightHand": "右手",
		"Spine": "脊柱",
		"Breasts": "乳房",
		"Legs": "腿部",
		"LeftLeg": "左腿",
		"LeftFoot": "左足",
		"RightLeg": "右腿",
		"RightFoot": "右足",
		"Tail": "尾巴",
		"Clothing": "服装",
		"Cloth": "衣服",
		"Earring": "耳饰",
		"Weapons": "武器",
		"Other": "其他",

		"LeftHandIvcs": "IVCS 左手",
		"RightHandIvcs": "IVCS 右手",
		"BreastsIvcs": "IVCS 乳房",
		"LeftFootIvcs": "IVCS 左足",
		"RightFootIvcs": "IVCS 右足",
		"GenitalsIvcs": "IVCS 生殖器",
		"PenisIvcs": "IVCS 阴茎",
		"VaginaIvcs": "IVCS 阴道",
		"BottomIvcs": "IVCS 下体",

		"SkelomaeWings": "Skelomae 翅膀",
		"SkelomaeWingsLeft": "Skelomae 左侧翅膀",
		"SkelomaeWingsRight": "Skelomae 右侧翅膀",
		"SkelomaeCreatures": "Skelomae 生物",
		"SkelomaeCreaturesLamia": "蛇女",
		"SkelomaeCreaturesGenetals": "生殖器",
		"SkelomaeCreaturesCentaur": "半人马",
		"SkelomaeCreaturesCentaurBody": "半人马身体",
		"SkelomaeCreaturesCentaurBodyFrontLegs": "前腿",
		"SkelomaeCreaturesCentaurBodyBackLegs": "后腿",
		"SkelomaeCreaturesCentaurTail": "尾巴",

		"CustomArms": "自定义骨架手臂",
		"CustomAbdomen": "自定义骨架腹部",
		"CustomLegs": "自定义骨架腿部"
	},

	"lightType": {
		"Directional": "太阳光（定向光）",
		"PointLight": "点光源",
		"SpotLight": "聚光灯",
		"AreaLight": "区域光"
	},

	"lightFalloff": {
		"Linear": "线性衰减",
		"Quadratic": "二次衰减",
		"Cubic": "三次衰减"
	},
	
	"misc": {
		"command_desc": "切换 Ktisis 主窗口。"
	}
}
